[
    {
        "id": "N5_0701",
        "level": "N5",
        "expression": "悩む",
        "kana": "なやむ",
        "tone": "②",
        "pos": "自動1",
        "meaning": "烦恼，苦恼",
        "examples": [
            {
                "ja": "将来[しょうらい]に悩[なや]みます。",
                "zh": "为未来烦恼。"
            },
            {
                "ja": "問題[もんだい]に悩[なや]みます。",
                "zh": "为问题苦恼。"
            },
            {
                "ja": "決[き]めかねて悩[なや]みます。",
                "zh": "犹豫不决而烦恼。"
            }
        ]
    },
    {
        "id": "N5_0702",
        "level": "N5",
        "expression": "習う",
        "kana": "ならう",
        "tone": "②",
        "pos": "他動1",
        "meaning": "学习；练习",
        "examples": [
            {
                "ja": "ギターを習[なら]います。",
                "zh": "学吉他。"
            },
            {
                "ja": "書道[しょどう]を習[なら]っています。",
                "zh": "在学习书法。"
            },
            {
                "ja": "先輩[せんぱい]から技[ぎ]術[じゅつ]を習[なら]います。",
                "zh": "向前辈学习技术。"
            }
        ]
    },
    {
        "id": "N5_0703",
        "level": "N5",
        "expression": "並ぶ",
        "kana": "ならぶ",
        "tone": "[0]",
        "pos": "自動1",
        "meaning": "排列",
        "examples": [
            {
                "ja": "列[れつ]で並[な]びます。",
                "zh": "排队。"
            },
            {
                "ja": "本[ほん]棚[だな]に本[ほん]が並[な]んでいます。",
                "zh": "书架上排着书。"
            },
            {
                "ja": "店[みせ]先[さき]に人[ひと]が並[な]びます。",
                "zh": "店门前有人排队。"
            }
        ]
    },
    {
        "id": "N5_0704",
        "level": "N5",
        "expression": "並べる",
        "kana": "ならべる",
        "tone": "[0]",
        "pos": "他動2",
        "meaning": "并肩，排列",
        "examples": [
            {
                "ja": "肩[かた]を並[な]べて歩[ある]きます。",
                "zh": "并肩走。"
            },
            {
                "ja": "本[ほん]を並[な]べます。",
                "zh": "排列书本。"
            },
            {
                "ja": "食材[しょくざい]を並[な]べます。",
                "zh": "摆放食材。"
            }
        ]
    },
    {
        "id": "N5_0705",
        "level": "N5",
        "expression": "なる",
        "kana": "なる",
        "tone": "①",
        "pos": "自動1",
        "meaning": "变成，成为",
        "examples": [
            {
                "ja": "先生[せんせい]になる。",
                "zh": "成为老师。"
            },
            {
                "ja": "病気[びょうき]になります。",
                "zh": "生病。"
            },
            {
                "ja": "静[しず]かになります。",
                "zh": "变安静。"
            }
        ]
    },
    {
        "id": "N5_0706",
        "level": "N5",
        "expression": "何",
        "kana": "なん",
        "tone": "①",
        "pos": "代",
        "meaning": "什么",
        "examples": [
            {
                "ja": "これは何[なん]ですか。",
                "zh": "这是什么？"
            },
            {
                "ja": "何[なん]の用[よう]ですか。",
                "zh": "有什么事吗？"
            },
            {
                "ja": "何[なん]と言[い]いましたか。",
                "zh": "说了什么？"
            }
        ]
    },
    {
        "id": "N5_0707",
        "level": "N5",
        "expression": "何～",
        "kana": "なん～",
        "tone": "",
        "pos": "接頭",
        "meaning": "多少……，几……",
        "examples": [
            {
                "ja": "何人[なんにん]出席[しゅっせき]したの。",
                "zh": "有几人参加了？"
            },
            {
                "ja": "何回[なんかい]も行[い]きました。",
                "zh": "去了好几次。"
            },
            {
                "ja": "何時[なんじ]に会[あ]いますか。",
                "zh": "几点见面？"
            }
        ]
    },
    {
        "id": "N5_0708",
        "level": "N5",
        "expression": "賑やか",
        "kana": "にぎやか",
        "tone": "②",
        "pos": "ナ形",
        "meaning": "喧闹，繁华",
        "examples": [
            {
                "ja": "賑[にぎ]やかな町[まち]です。",
                "zh": "喧闹的街道。"
            },
            {
                "ja": "パーティーは賑[にぎ]やかでした。",
                "zh": "派对很热闹。"
            },
            {
                "ja": "祭[まつ]りで賑[にぎ]やかになります。",
                "zh": "因节日而变得热闹。"
            }
        ]
    },
    {
        "id": "N5_0709",
        "level": "N5",
        "expression": "肉",
        "kana": "にく",
        "tone": "②",
        "pos": "名",
        "meaning": "肉，肉类",
        "examples": [
            {
                "ja": "肉[にく]を食[た]べます。",
                "zh": "吃肉。"
            },
            {
                "ja": "肉[にく]料理[りょうり]を作[つく]ります。",
                "zh": "做肉菜。"
            },
            {
                "ja": "肉[にく]が好[す]きです。",
                "zh": "喜欢肉。"
            }
        ]
    },
    {
        "id": "N5_0710",
        "level": "N5",
        "expression": "～難い",
        "kana": "～にくい",
        "tone": "②",
        "pos": "接尾",
        "meaning": "难的",
        "examples": [
            {
                "ja": "読[よ]みにくい本[ほん]です。",
                "zh": "难以读懂的书。"
            },
            {
                "ja": "食[た]べにくいです。",
                "zh": "很难吃（指吃起来费劲）。"
            },
            {
                "ja": "説明[せつめい]しにくい問題[もんだい]です。",
                "zh": "难以说明的问题。"
            }
        ]
    },
    {
        "id": "N5_0711",
        "level": "N5",
        "expression": "西",
        "kana": "にし",
        "tone": "[0]",
        "pos": "名",
        "meaning": "西方",
        "examples": [
            {
                "ja": "日[ひ]が西[にし]へ沈[しず]みます。",
                "zh": "太阳落向西方。"
            },
            {
                "ja": "西[にし]の空[そら]が赤[あか]いです。",
                "zh": "西边的天空是红色的。"
            },
            {
                "ja": "西[にし]の方角[ほうがく]に行[い]きます。",
                "zh": "往西方去。"
            }
        ]
    },
    {
        "id": "N5_0712",
        "level": "N5",
        "expression": "～日",
        "kana": "～にち",
        "tone": "",
        "pos": "接尾",
        "meaning": "……号；……天",
        "examples": [
            {
                "ja": "今日[きょう]は15日[にち]です。",
                "zh": "今天是15号。"
            },
            {
                "ja": "3日[みっか]もかかりました。",
                "zh": "花了三天。"
            },
            {
                "ja": "何日[なんにち]滞在[たいざい]しますか。",
                "zh": "逗留几天？"
            }
        ]
    },
    {
        "id": "N5_0713",
        "level": "N5",
        "expression": "日曜日",
        "kana": "にちようび",
        "tone": "③",
        "pos": "名",
        "meaning": "周日",
        "examples": [
            {
                "ja": "日曜日[にちようび]は休[やす]みです。",
                "zh": "周日休息。"
            },
            {
                "ja": "次[つぎ]の日曜日[にちようび]に会[あ]いましょう。",
                "zh": "下个周日见吧。"
            },
            {
                "ja": "楽[たの]しい日曜日[にちようび]を過[す]ごします。",
                "zh": "度过愉快的周日。"
            }
        ]
    },
    {
        "id": "N5_0714",
        "level": "N5",
        "expression": "日本",
        "kana": "にほん",
        "tone": "②",
        "pos": "名",
        "meaning": "日本",
        "examples": [
            {
                "ja": "日本[にほん]料理[りょうり]はおいしいです。",
                "zh": "日式料理很好吃。"
            },
            {
                "ja": "日本[にほん]に行[い]きたいです。",
                "zh": "想去日本。"
            },
            {
                "ja": "日本[にほん]の文化[ぶんか]を学[まな]びます。",
                "zh": "学习日本文化。"
            }
        ]
    },
    {
        "id": "N5_0715",
        "level": "N5",
        "expression": "日本語",
        "kana": "にほんご",
        "tone": "[0]",
        "pos": "名",
        "meaning": "日语",
        "examples": [
            {
                "ja": "日本語[にほんご]を勉強[べんきょう]します。",
                "zh": "学日语。"
            },
            {
                "ja": "日本語[にほんご]が話[はな]せます。",
                "zh": "会说日语。"
            },
            {
                "ja": "難[むずか]しい日本語[にほんご]を使[つか]います。",
                "zh": "使用难懂的日语。"
            }
        ]
    },
    {
        "id": "N5_0716",
        "level": "N5",
        "expression": "荷物",
        "kana": "にもつ",
        "tone": "①",
        "pos": "名",
        "meaning": "行李",
        "examples": [
            {
                "ja": "荷物[にもつ]を運[はこ]びます。",
                "zh": "搬运行李。"
            },
            {
                "ja": "荷物[にもつ]を預[あず]けます。",
                "zh": "寄存行李。"
            },
            {
                "ja": "重[おも]い荷物[にもつ]を持[も]ちます。",
                "zh": "拿着沉重的行李。"
            }
        ]
    },
    {
        "id": "N5_0717",
        "level": "N5",
        "expression": "入学式",
        "kana": "にゅうがくしき",
        "tone": "[0]",
        "pos": "名",
        "meaning": "入学仪式，开学典礼",
        "examples": [
            {
                "ja": "入学式[にゅうがくしき]に参加[さんか]します。",
                "zh": "参加开学典礼。"
            },
            {
                "ja": "入学式[にゅうがくしき]の写真[しゃしん]を撮[と]ります。",
                "zh": "拍开学典礼的照片。"
            },
            {
                "ja": "桜[さくら]の季節[きせつ]に入学式[にゅうがくしき]があります。",
                "zh": "在樱花季节有开学典礼。"
            }
        ]
    },
    {
        "id": "N5_0718",
        "level": "N5",
        "expression": "news",
        "kana": "ニュース",
        "tone": "①",
        "pos": "名",
        "meaning": "新闻",
        "examples": [
            {
                "ja": "ニュースを放送[ほうそう]します。",
                "zh": "播放新闻。"
            },
            {
                "ja": "朝[あさ]のニュースを見[み]ます。",
                "zh": "看早间新闻。"
            },
            {
                "ja": "良[よ]いニュースを聞[き]きました。",
                "zh": "听到了好消息。"
            }
        ]
    },
    {
        "id": "N5_0719",
        "level": "N5",
        "expression": "庭",
        "kana": "にわ",
        "tone": "[0]",
        "pos": "名",
        "meaning": "庭院，院子",
        "examples": [
            {
                "ja": "庭[にわ]が広[ひろ]いです。",
                "zh": "院子很宽敞。"
            },
            {
                "ja": "庭[にわ]に花[はな]を植[う]えます。",
                "zh": "在院子里种花。"
            },
            {
                "ja": "庭[にわ]で遊[あそ]びます。",
                "zh": "在院子里玩。"
            }
        ]
    },
    {
        "id": "N5_0720",
        "level": "N5",
        "expression": "～人",
        "kana": "～にん",
        "tone": "",
        "pos": "接尾",
        "meaning": "……人",
        "examples": [
            {
                "ja": "一[ひと]クラスで30人[にん]ぐらいいます。",
                "zh": "一个班大概有30人。"
            },
            {
                "ja": "3人[にん]で食事[しょくじ]します。",
                "zh": "三人一起吃饭。"
            },
            {
                "ja": "何人[なんにん]家族[かぞく]ですか。",
                "zh": "家里有几口人？"
            }
        ]
    },
    {
        "id": "N5_0721",
        "level": "N5",
        "expression": "人気",
        "kana": "にんき",
        "tone": "[0]",
        "pos": "名",
        "meaning": "人气，声望，人缘",
        "examples": [
            {
                "ja": "人気[にんき]があります。",
                "zh": "有人气。"
            },
            {
                "ja": "人気[にんき]商品[しょうひん]です。",
                "zh": "受欢迎的商品。"
            },
            {
                "ja": "彼[かれ]はクラスで人気[にんき]があります。",
                "zh": "他在班上很受欢迎。"
            }
        ]
    },
    {
        "id": "N5_0722",
        "level": "N5",
        "expression": "人間",
        "kana": "にんげん",
        "tone": "[0]",
        "pos": "名",
        "meaning": "人,人类",
        "examples": [
            {
                "ja": "人間[にんげん]関係[かんけい]が大切[たいせつ]です。",
                "zh": "人际关系很重要。"
            },
            {
                "ja": "人間[にんげん]は考[かんが]える葦[あし]です。",
                "zh": "人是会思想的芦苇。"
            },
            {
                "ja": "優[やさ]しい人間[にんげん]になりたいです。",
                "zh": "想成为温柔的人。"
            }
        ]
    },
    {
        "id": "N5_0723",
        "level": "N5",
        "expression": "脱ぐ",
        "kana": "ぬぐ",
        "tone": "①",
        "pos": "他動1",
        "meaning": "摘掉，脱掉",
        "examples": [
            {
                "ja": "帽子[ぼうし]を脱[ぬ]ぎます。",
                "zh": "摘掉帽子。"
            },
            {
                "ja": "靴[くつ]を脱[ぬ]ぎます。",
                "zh": "脱鞋。"
            },
            {
                "ja": "服[ふく]を脱[ぬ]ぎます。",
                "zh": "脱衣服。"
            }
        ]
    },
    {
        "id": "N5_0724",
        "level": "N5",
        "expression": "温い",
        "kana": "ぬるい",
        "tone": "②",
        "pos": "イ形",
        "meaning": "微温的；（性格等）不严格的",
        "examples": [
            {
                "ja": "温[ぬる]いお茶[ちゃ]を飲[の]みます。",
                "zh": "喝温茶。"
            },
            {
                "ja": "温[ぬる]い性格[せいかく]です。",
                "zh": "不温不火的性格。"
            },
            {
                "ja": "お風呂[ふろ]がまだ温[ぬる]いです。",
                "zh": "洗澡水还只有微温。"
            }
        ]
    },
    {
        "id": "N5_0725",
        "level": "N5",
        "expression": "ね",
        "kana": "ね",
        "tone": "①",
        "pos": "助",
        "meaning": "(表示感叹）啊，呀；（表示轻微的叮问）吧；（打招呼时）喂，唉",
        "examples": [
            {
                "ja": "今[きょう]日は暑[あつ]いですね。",
                "zh": "今天好热呀。"
            },
            {
                "ja": "もう終[お]わったね。",
                "zh": "已经结束了吧？"
            },
            {
                "ja": "ね、今[いま]聞[き]いている？",
                "zh": "喂，现在在听吗？"
            }
        ]
    },
    {
        "id": "N5_0726",
        "level": "N5",
        "expression": "ねえ",
        "kana": "ねえ",
        "tone": "①",
        "pos": "嘆",
        "meaning": "(打招呼时）喂，唉",
        "examples": [
            {
                "ja": "ねえ、ちょっと聞[き]いて。",
                "zh": "喂，听我说一下。"
            },
            {
                "ja": "ねえ、あの人[ひと]知[し]ってる？",
                "zh": "喂，认识那个人吗？"
            },
            {
                "ja": "ねえ、早[はや]く遊[あそ]ぼうよ。",
                "zh": "喂，快点玩吧。"
            }
        ]
    },
    {
        "id": "N5_0727",
        "level": "N5",
        "expression": "necktie",
        "kana": "ネクタイ",
        "tone": "①",
        "pos": "名",
        "meaning": "领带",
        "examples": [
            {
                "ja": "ネクタイを締[し]めます。",
                "zh": "系领带。"
            },
            {
                "ja": "赤[あか]いネクタイを買[か]いました。",
                "zh": "买了红色的领带。"
            },
            {
                "ja": "スーツにネクタイを合[あ]わせます。",
                "zh": "西装搭配领带。"
            }
        ]
    },
    {
        "id": "N5_0728",
        "level": "N5",
        "expression": "猫",
        "kana": "ねこ",
        "tone": "①",
        "pos": "名",
        "meaning": "猫",
        "examples": [
            {
                "ja": "猫[ねこ]を飼[か]っています。",
                "zh": "养着猫。"
            },
            {
                "ja": "白[しろ]い猫[ねこ]がいます。",
                "zh": "有一只白猫。"
            },
            {
                "ja": "猫[ねこ]が魚[さかな]を食[た]べました。",
                "zh": "猫吃了鱼。"
            }
        ]
    },
    {
        "id": "N5_0729",
        "level": "N5",
        "expression": "寝る",
        "kana": "ねる",
        "tone": "[0]",
        "pos": "自動2",
        "meaning": "睡觉;躺着",
        "examples": [
            {
                "ja": "寝[ね]る前[まえ]にミルクを飲[の]みます。",
                "zh": "睡觉前喝牛奶。"
            },
            {
                "ja": "早[はや]く寝[ね]てください。",
                "zh": "请早点睡。"
            },
            {
                "ja": "休[やす]みの日[ひ]は昼[ひる]まで寝[ね]ています。",
                "zh": "休息日睡到中午。"
            }
        ]
    },
    {
        "id": "N5_0730",
        "level": "N5",
        "expression": "年",
        "kana": "ねん",
        "tone": "①",
        "pos": "名",
        "meaning": "年，一年",
        "examples": [
            {
                "ja": "年[ねん]に一度[いちど]帰国[きこく]します。",
                "zh": "—年回一次国。"
            },
            {
                "ja": "年[ねん]の始[はじ]めに目標[もくひょう]を立[た]てます。",
                "zh": "在年初制定目标。"
            },
            {
                "ja": "良[よ]い年[ねん]になりますように。",
                "zh": "希望是个好年头。"
            }
        ]
    },
    {
        "id": "N5_0731",
        "level": "N5",
        "expression": "～年",
        "kana": "～ねん",
        "tone": "",
        "pos": "接尾",
        "meaning": "……年",
        "examples": [
            {
                "ja": "2004年[ねん]大学[だいがく]を卒業[そつぎょう]しました。",
                "zh": "2004年大学毕业。"
            },
            {
                "ja": "3年[ねん]かかって卒業[そつぎょう]しました。",
                "zh": "花了三年毕业。"
            },
            {
                "ja": "何[なん]年[ねん]日本[にほん]にいますか。",
                "zh": "在日本呆了几年？"
            }
        ]
    },
    {
        "id": "N5_0732",
        "level": "N5",
        "expression": "年賀状",
        "kana": "ねんがじょう",
        "tone": "③[0]",
        "pos": "名",
        "meaning": "贺年片，贺年卡",
        "examples": [
            {
                "ja": "友達[ともだち]に年賀状[ねんがじょう]を書[か]きます。",
                "zh": "给朋友写贺年卡。"
            },
            {
                "ja": "年賀状[ねんがじょう]が届[とど]きました。",
                "zh": "贺年卡送到了。"
            },
            {
                "ja": "年賀状[ねんがじょう]の準備[じゅんび]をします。",
                "zh": "准备贺年卡。"
            }
        ]
    },
    {
        "id": "N5_0733",
        "level": "N5",
        "expression": "年金",
        "kana": "ねんきん",
        "tone": "[0]",
        "pos": "名",
        "meaning": "年金，退休金",
        "examples": [
            {
                "ja": "年金[ねんきん]で暮[く]らします。",
                "zh": "依靠退休金生活。"
            },
            {
                "ja": "年金[ねんきん]を払[はら]います。",
                "zh": "缴纳养老金。"
            },
            {
                "ja": "将来[しょうらい]の年金[ねんきん]が心配[しんぱい]です。",
                "zh": "担心将来的养老金。"
            }
        ]
    },
    {
        "id": "N5_0734",
        "level": "N5",
        "expression": "note",
        "kana": "ノート",
        "tone": "①",
        "pos": "名",
        "meaning": "笔记本，备忘录",
        "examples": [
            {
                "ja": "要点[ようてん]をノートに書[か]きます。",
                "zh": "把要点记在笔记本上。"
            },
            {
                "ja": "新[あたら]しいノートを買[か]いました。",
                "zh": "买了新笔记本。"
            },
            {
                "ja": "ノートを借[か]してもいいですか。",
                "zh": "可以借下笔记本吗？"
            }
        ]
    },
    {
        "id": "N5_0735",
        "level": "N5",
        "expression": "のど",
        "kana": "のど",
        "tone": "①",
        "pos": "名",
        "meaning": "咽喉，嗓子",
        "examples": [
            {
                "ja": "のどが渴[かわ]きました。",
                "zh": "嗓子干。"
            },
            {
                "ja": "のどが痛[いた]いです。",
                "zh": "嗓子疼。"
            },
            {
                "ja": "風邪[かぜ]でのどが腫[は]れました。",
                "zh": "因为感冒嗓子肿了。"
            }
        ]
    },
    {
        "id": "N5_0736",
        "level": "N5",
        "expression": "登る/上る",
        "kana": "のぼる",
        "tone": "[0]",
        "pos": "自動1",
        "meaning": "登上，爬上；到达",
        "examples": [
            {
                "ja": "山[やま]の頂上[ちょうじょう]に登[のぼ]ります。",
                "zh": "登上山頂。"
            },
            {
                "ja": "参加[さんか]者[しゃ]は50人[にん]にも上[のぼ]ります。",
                "zh": "参加人数达50人。"
            },
            {
                "ja": "階段[かいだん]を登[のぼ]ります。",
                "zh": "爬楼梯。"
            }
        ]
    },
    {
        "id": "N5_0737",
        "level": "N5",
        "expression": "昼ご飯",
        "kana": "ひるごはん",
        "tone": "③",
        "pos": "名",
        "meaning": "午饭",
        "examples": [
            {
                "ja": "昼[ひる]ご飯[はん]を食[た]べます。",
                "zh": "吃午饭。"
            },
            {
                "ja": "一緒[いっしょ]に昼[ひる]ご飯[はん]に行[い]きませんか。",
                "zh": "一起去吃午饭吗？"
            },
            {
                "ja": "昼[ひる]ご飯[はん]は何[なに]がいいですか。",
                "zh": "午饭吃什么好？"
            }
        ]
    },
    {
        "id": "N5_0738",
        "level": "N5",
        "expression": "広い",
        "kana": "ひろい",
        "tone": "②",
        "pos": "イ形",
        "meaning": "宽广的，宽敞的;广泛的，广博的",
        "examples": [
            {
                "ja": "広[ひろ]い庭[にわ]があります。",
                "zh": "有宽阔的庭院。"
            },
            {
                "ja": "彼[かれ]は心[こころ]が広[ひろ]いです。",
                "zh": "他心胸开阔。"
            },
            {
                "ja": "部屋[へや]が広[ひろ]くて快適[かいてき]です。",
                "zh": "房间宽敞舒适。"
            }
        ]
    },
    {
        "id": "N5_0739",
        "level": "N5",
        "expression": "film",
        "kana": "フィルム",
        "tone": "①",
        "pos": "名",
        "meaning": "胶卷",
        "examples": [
            {
                "ja": "カメラにフィルムを入[い]れます。",
                "zh": "给照相机装胶卷。"
            },
            {
                "ja": "古[ふる]いフィルムを見[み]つけました。",
                "zh": "找到了旧胶卷。"
            },
            {
                "ja": "フィルム映画[えいが]を見[み]ます。",
                "zh": "看胶片电影。"
            }
        ]
    },
    {
        "id": "N5_0740",
        "level": "N5",
        "expression": "封筒",
        "kana": "ふうとう",
        "tone": "[0]",
        "pos": "名",
        "meaning": "信封",
        "examples": [
            {
                "ja": "手紙[てがみ]を封筒[ふうとう]に入[い]れます。",
                "zh": "将信放入信封里。"
            },
            {
                "ja": "封筒[ふうとう]に切手[きって]を貼[は]ります。",
                "zh": "在信封上贴邮票。"
            },
            {
                "ja": "大[おお]きい封筒[ふうとう]が必要[ひつよう]です。",
                "zh": "需要大信封。"
            }
        ]
    },
    {
        "id": "N5_0741",
        "level": "N5",
        "expression": "pool",
        "kana": "プール",
        "tone": "①",
        "pos": "名",
        "meaning": "游泳池",
        "examples": [
            {
                "ja": "夏[なつ]はプールに行[い]きます。",
                "zh": "夏天去游泳池。"
            },
            {
                "ja": "ホテルにプールがあります。",
                "zh": "酒店里有游泳池。"
            },
            {
                "ja": "プールで泳[およ]ぎます。",
                "zh": "在泳池游泳。"
            }
        ]
    },
    {
        "id": "N5_0742",
        "level": "N5",
        "expression": "fork",
        "kana": "フォーク",
        "tone": "①",
        "pos": "名",
        "meaning": "叉子",
        "examples": [
            {
                "ja": "フォークを使[つか]います。",
                "zh": "使用叉子。"
            },
            {
                "ja": "ナイフとフォークで食[た]べます。",
                "zh": "用刀叉吃。"
            },
            {
                "ja": "フォークを落[お]としました。",
                "zh": "叉子掉了。"
            }
        ]
    },
    {
        "id": "N5_0743",
        "level": "N5",
        "expression": "服",
        "kana": "ふく",
        "tone": "②",
        "pos": "名",
        "meaning": "衣服",
        "examples": [
            {
                "ja": "服[ふく]を着[き]ます。",
                "zh": "穿衣服。"
            },
            {
                "ja": "服[ふく]を脱[ぬ]ぎます。",
                "zh": "脱衣服。"
            },
            {
                "ja": "新[あたら]しい服[ふく]を買[か]いました。",
                "zh": "买了新衣服。"
            }
        ]
    },
    {
        "id": "N5_0744",
        "level": "N5",
        "expression": "吹く",
        "kana": "ふく",
        "tone": "①②",
        "pos": "自他動1",
        "meaning": "(自）吹风，刮风;(他）吹，喷",
        "examples": [
            {
                "ja": "強[つよ]い風[かぜ]が吹[ふ]きます。",
                "zh": "刮大风。"
            },
            {
                "ja": "笛[ふえ]を吹[ふ]きます。",
                "zh": "吹笛子。"
            },
            {
                "ja": "春[はる]の風[かぜ]が吹[ふ]いています。",
                "zh": "吹着春风。"
            }
        ]
    },
    {
        "id": "N5_0745",
        "level": "N5",
        "expression": "二つ",
        "kana": "ふたつ",
        "tone": "③",
        "pos": "名",
        "meaning": "两个；两岁",
        "examples": [
            {
                "ja": "りんごが二[ふた]つあります。",
                "zh": "有两个苹果。"
            },
            {
                "ja": "弟[おとうと]は二[ふた]つになります。",
                "zh": "弟弟两岁了。"
            },
            {
                "ja": "お願[ねが]いが二[ふた]つあります。",
                "zh": "有两个请求。"
            }
        ]
    },
    {
        "id": "N5_0746",
        "level": "N5",
        "expression": "豚肉",
        "kana": "ぶたにく",
        "tone": "[0]",
        "pos": "名",
        "meaning": "猪肉",
        "examples": [
            {
                "ja": "豚肉[ぶたにく]で作[つく]った料理[りょうり]です。",
                "zh": "用猪肉做的菜。"
            },
            {
                "ja": "豚肉[ぶたにく]を買[か]います。",
                "zh": "买猪肉。"
            },
            {
                "ja": "今日[きょう]は豚肉[ぶたにく]料理[りょうり]です。",
                "zh": "今天是猪肉料理。"
            }
        ]
    },
    {
        "id": "N5_0747",
        "level": "N5",
        "expression": "二人",
        "kana": "ふたり",
        "tone": "③",
        "pos": "名",
        "meaning": "两个人",
        "examples": [
            {
                "ja": "二人[ふたり]が来[き]ました。",
                "zh": "来了两个人。"
            },
            {
                "ja": "二人[ふたり]で映画[えいが]を見[み]ます。",
                "zh": "两个人看电影。"
            },
            {
                "ja": "二人[ふたり]とも学生[がくせい]です。",
                "zh": "两个人都是学生。"
            }
        ]
    },
    {
        "id": "N5_0748",
        "level": "N5",
        "expression": "二日",
        "kana": "ふつか",
        "tone": "[0]",
        "pos": "名",
        "meaning": "两天;二号",
        "examples": [
            {
                "ja": "1泊[いっぱく]2日[ふつか]の旅行[りょこう]に行[い]きます。",
                "zh": "去两天一夜的旅行。"
            },
            {
                "ja": "2月[にがつ]2日[ふつか]です。",
                "zh": "二月二号。"
            },
            {
                "ja": "あと二日[ふつか]で試験[しけん]です。",
                "zh": "还有两天就考试了。"
            }
        ]
    },
    {
        "id": "N5_0749",
        "level": "N5",
        "expression": "太い",
        "kana": "ふとい",
        "tone": "②",
        "pos": "イ形",
        "meaning": "胖的;粗的",
        "examples": [
            {
                "ja": "足[あし]が太[ふと]いです。",
                "zh": "腿粗。"
            },
            {
                "ja": "太[ふと]い眉[まゆ]をしています。",
                "zh": "长着粗眉。"
            },
            {
                "ja": "太[ふと]い木[き]があります。",
                "zh": "有棵粗树。"
            }
        ]
    },
    {
        "id": "N5_0750",
        "level": "N5",
        "expression": "船",
        "kana": "ふね",
        "tone": "①",
        "pos": "名",
        "meaning": "船",
        "examples": [
            {
                "ja": "船[ふね]に乗[の]ります。",
                "zh": "坐船。"
            },
            {
                "ja": "大[おお]きな船[ふね]を見[み]ました。",
                "zh": "看见了大船。"
            },
            {
                "ja": "船[ふね]が港[みなと]に着[つ]きます。",
                "zh": "船到达港口。"
            }
        ]
    },
    {
        "id": "N5_0751",
        "level": "N5",
        "expression": "冬",
        "kana": "ふゆ",
        "tone": "②",
        "pos": "名",
        "meaning": "冬天，冬季",
        "examples": [
            {
                "ja": "冬[ふゆ]は寒[さむ]いです。",
                "zh": "冬天很冷。"
            },
            {
                "ja": "冬[ふゆ]のスポーツを楽[たの]しみます。",
                "zh": "享受冬季运动。"
            },
            {
                "ja": "冬[ふゆ]が来[き]ました。",
                "zh": "冬天来了。"
            }
        ]
    },
    {
        "id": "N5_0752",
        "level": "N5",
        "expression": "冬休み",
        "kana": "ふゆやすみ",
        "tone": "③",
        "pos": "名",
        "meaning": "寒假",
        "examples": [
            {
                "ja": "冬休[ふゆやす]みは短[みじか]いです。",
                "zh": "寒假很短。"
            },
            {
                "ja": "冬休[ふゆやす]みにスキーに行[い]きます。",
                "zh": "寒假去滑雪。"
            },
            {
                "ja": "冬休[ふゆやす]みの計画[けいかく]を立[た]てます。",
                "zh": "制定寒假计划。"
            }
        ]
    },
    {
        "id": "N5_0753",
        "level": "N5",
        "expression": "振る",
        "kana": "ふる",
        "tone": "[0]",
        "pos": "他動1",
        "meaning": "挥，摇，摆",
        "examples": [
            {
                "ja": "手[て]を振[ふ]ります。",
                "zh": "挥手。"
            },
            {
                "ja": "首[くび]を縦[たて]に振[ふ]ります。",
                "zh": "点头（直译：纵向摇头）。"
            },
            {
                "ja": "犬[いぬ]が尻尾[しっぽ]を振[ふ]ります。",
                "zh": "狗摇尾巴。"
            }
        ]
    },
    {
        "id": "N5_0754",
        "level": "N5",
        "expression": "降る",
        "kana": "ふる",
        "tone": "①",
        "pos": "自動1",
        "meaning": "下;降落，飘落",
        "examples": [
            {
                "ja": "雪[ゆき]が降[ふ]ります。",
                "zh": "下雪。"
            },
            {
                "ja": "雨[あめ]が降[ふ]ってきました。",
                "zh": "下起雨来了。"
            },
            {
                "ja": "桜[さくら]の花[はな]びらが降[ふ]ります。",
                "zh": "樱花花瓣飘落。"
            }
        ]
    },
    {
        "id": "N5_0755",
        "level": "N5",
        "expression": "古い",
        "kana": "ふるい",
        "tone": "②",
        "pos": "イ形",
        "meaning": "古老的；旧的",
        "examples": [
            {
                "ja": "古[ふる]い話[はなし]です。",
                "zh": "这是个古老的故事。"
            },
            {
                "ja": "古[ふる]い椅子[いす]を捨[す]てます。",
                "zh": "扔掉旧椅子。"
            },
            {
                "ja": "これは古[ふる]い建物[たてもの]です。",
                "zh": "这是栋古老的建筑物。"
            }
        ]
    },
    {
        "id": "N5_0756",
        "level": "N5",
        "expression": "故郷/故里",
        "kana": "ふるさと",
        "tone": "②",
        "pos": "名",
        "meaning": "故乡，家乡",
        "examples": [
            {
                "ja": "故郷[ふるさと]のお土産[みやげ]です。",
                "zh": "家乡的特产。"
            },
            {
                "ja": "故郷[ふるさと]へ帰[かえ]ります。",
                "zh": "回故乡。"
            },
            {
                "ja": "故郷[ふるさと]が懐[なつ]かしいです。",
                "zh": "怀念故乡。"
            }
        ]
    },
    {
        "id": "N5_0757",
        "level": "N5",
        "expression": "風呂",
        "kana": "ふろ",
        "tone": "②",
        "pos": "名",
        "meaning": "澡堂;洗澡盆，洗澡水",
        "examples": [
            {
                "ja": "お風呂[ふろ]に入[はい]ります。",
                "zh": "去洗澡。"
            },
            {
                "ja": "お風呂[ふろ]が熱[あつ]いです。",
                "zh": "洗澡水烫。"
            },
            {
                "ja": "お風呂[ふろ]を沸[わ]かします。",
                "zh": "烧洗澡水。"
            }
        ]
    },
    {
        "id": "N5_0758",
        "level": "N5",
        "expression": "～分",
        "kana": "～ふん",
        "tone": "",
        "pos": "接尾",
        "meaning": "……分，……分钟",
        "examples": [
            {
                "ja": "8時[じ]5分[ごふん]です。",
                "zh": "八点零五分。"
            },
            {
                "ja": "話[はなし]を2分[にふん]以内[いない]にまとめます。",
                "zh": "把话归纳至两分钟内。"
            },
            {
                "ja": "あと10分[じゅっぷん]待[ま]ってください。",
                "zh": "请再等10分钟。"
            }
        ]
    },
    {
        "id": "N5_0759",
        "level": "N5",
        "expression": "文章",
        "kana": "ぶんしょう",
        "tone": "①",
        "pos": "名",
        "meaning": "文章,作品",
        "examples": [
            {
                "ja": "文章[ぶんしょう]を書[か]きます。",
                "zh": "写文章。"
            },
            {
                "ja": "文章[ぶんしょう]を読[よ]みます。",
                "zh": "读文章。"
            },
            {
                "ja": "短[みじか]い文章[ぶんしょう]を作[つく]ります。",
                "zh": "写短文。"
            }
        ]
    },
    {
        "id": "N5_0760",
        "level": "N5",
        "expression": "page",
        "kana": "ページ",
        "tone": "[0]",
        "pos": "接尾*名",
        "meaning": "页，页面",
        "examples": [
            {
                "ja": "次[つぎ]のページを開[ひら]きます。",
                "zh": "翻开下一页。"
            },
            {
                "ja": "ホームページを見[み]ます。",
                "zh": "看主页。"
            },
            {
                "ja": "10ページを読[よ]んでください。",
                "zh": "请读第10页。"
            }
        ]
    },
    {
        "id": "N5_0761",
        "level": "N5",
        "expression": "下手",
        "kana": "へた",
        "tone": "②",
        "pos": "ナ形",
        "meaning": "不擅长的，笨拙的",
        "examples": [
            {
                "ja": "歌[うた]が下手[へた]です。",
                "zh": "不会唱歌。"
            },
            {
                "ja": "下手[へた]な絵[え]を描[か]きました。",
                "zh": "画得很烂的画。"
            },
            {
                "ja": "字[じ]が下手[へた]です。",
                "zh": "字写得不好。"
            }
        ]
    },
    {
        "id": "N5_0762",
        "level": "N5",
        "expression": "bed",
        "kana": "ベッド",
        "tone": "①",
        "pos": "名",
        "meaning": "床",
        "examples": [
            {
                "ja": "シングルベッドを買[か]いました。",
                "zh": "买了单人床。"
            },
            {
                "ja": "ダブルベットで寝[ね]ます。",
                "zh": "睡双人床。"
            },
            {
                "ja": "ベッドに入[はい]ります。",
                "zh": "上床睡觉。"
            }
        ]
    },
    {
        "id": "N5_0763",
        "level": "N5",
        "expression": "pet",
        "kana": "ペット",
        "tone": "①",
        "pos": "名",
        "meaning": "宠物",
        "examples": [
            {
                "ja": "ペットフードをあげる。",
                "zh": "给宠物饲料。"
            },
            {
                "ja": "ペットを飼[か]っていますか。",
                "zh": "你养宠物吗？"
            },
            {
                "ja": "ペットと散歩[さんぽ]します。",
                "zh": "和宠物散步。"
            }
        ]
    },
    {
        "id": "N5_0764",
        "level": "N5",
        "expression": "へや",
        "kana": "部屋",
        "tone": "②",
        "pos": "名",
        "meaning": "房间",
        "examples": [
            {
                "ja": "部屋[へや]に入[はい]ります。",
                "zh": "进入房间。"
            },
            {
                "ja": "部屋[へや]を掃除[そうじ]します。",
                "zh": "打扫房间。"
            },
            {
                "ja": "広[ひろ]い部屋[へや]です。",
                "zh": "宽敞的房间。"
            }
        ]
    },
    {
        "id": "N5_0765",
        "level": "N5",
        "expression": "へん",
        "kana": "辺",
        "tone": "[0]",
        "pos": "名",
        "meaning": "附近，左右",
        "examples": [
            {
                "ja": "山[やま]の辺[へん]に蛇[へび]がいます。",
                "zh": "山那一带有蛇。"
            },
            {
                "ja": "この辺[へん]にしておきましょう。",
                "zh": "就到这儿吧。"
            },
            {
                "ja": "駅[えき]の辺[へん]で会[あ]います。",
                "zh": "在车站附近见面。"
            }
        ]
    },
    {
        "id": "N5_0766",
        "level": "N5",
        "expression": "pen",
        "kana": "ペン",
        "tone": "①",
        "pos": "名",
        "meaning": "钢笔",
        "examples": [
            {
                "ja": "ペンで書[か]きます。",
                "zh": "用钢笔写。"
            },
            {
                "ja": "ペンを貸[か]してください。",
                "zh": "请借给我钢笔。"
            },
            {
                "ja": "赤[あか]いペンを持[も]っています。",
                "zh": "有红色的钢笔。"
            }
        ]
    },
    {
        "id": "N5_0767",
        "level": "N5",
        "expression": "勉強",
        "kana": "べんきょう",
        "tone": "[0]",
        "pos": "名*自他動3",
        "meaning": "学习",
        "examples": [
            {
                "ja": "日本語[にほんご]を勉強[べんきょう]します。",
                "zh": "学习日语。"
            },
            {
                "ja": "受験[じゅけん]勉強[べんきょう]をしています。",
                "zh": "正在进行应试学习。"
            },
            {
                "ja": "毎日[まいにち]勉強[べんきょう]します。",
                "zh": "每天学习。"
            }
        ]
    },
    {
        "id": "N5_0768",
        "level": "N5",
        "expression": "弁当",
        "kana": "べんとう",
        "tone": "③",
        "pos": "名",
        "meaning": "便当，盒饭",
        "examples": [
            {
                "ja": "お弁当[べんとう]を作[つく]ります。",
                "zh": "做便当。"
            },
            {
                "ja": "おいしいお弁当[べんとう]です。",
                "zh": "好吃的便当。"
            },
            {
                "ja": "コンビニでお弁当[べんとう]を買[か]います。",
                "zh": "在便利店买便当。"
            }
        ]
    },
    {
        "id": "N5_0769",
        "level": "N5",
        "expression": "便利",
        "kana": "べんり",
        "tone": "①",
        "pos": "名*ナ形",
        "meaning": "方便;方便的，便利的",
        "examples": [
            {
                "ja": "便利[べんり]を与[あた]えます。",
                "zh": "提供方便。"
            },
            {
                "ja": "このマンションは駅[えき]に近[ちか]いから、便利[べんり]です。",
                "zh": "这座公寓靠近车站，交通很便利。"
            },
            {
                "ja": "便利[べんり]な道具[どうぐ]を使[つか]います。",
                "zh": "使用便利的工具。"
            }
        ]
    },
    {
        "id": "N5_0770",
        "level": "N5",
        "expression": "方",
        "kana": "ほう",
        "tone": "①",
        "pos": "名",
        "meaning": "方，方向",
        "examples": [
            {
                "ja": "東[ひがし]の方[ほう]を見[み]ます。",
                "zh": "看着东边。"
            },
            {
                "ja": "あの方[ほう]が好[す]きです。",
                "zh": "喜欢那个方向（比方说做法，方面）。"
            },
            {
                "ja": "学校[がっこう]の方[ほう]へ行[い]きます。",
                "zh": "往学校那边走。"
            }
        ]
    },
    {
        "id": "N5_0771",
        "level": "N5",
        "expression": "帽子",
        "kana": "ぼうし",
        "tone": "[0]",
        "pos": "名",
        "meaning": "帽子",
        "examples": [
            {
                "ja": "帽子[ぼうし]を被[かぶ]ります。",
                "zh": "戴帽子。"
            },
            {
                "ja": "帽子[ぼうし]を脱[ぬ]ぎます。",
                "zh": "摘帽。"
            },
            {
                "ja": "白[しろ]い帽子[ぼうし]を買[か]いました。",
                "zh": "买了白色的帽子。"
            }
        ]
    },
    {
        "id": "N5_0772",
        "level": "N5",
        "expression": "boat",
        "kana": "ボート",
        "tone": "①",
        "pos": "名",
        "meaning": "小船，小艇",
        "examples": [
            {
                "ja": "ボートを漕[こ]ぎます。",
                "zh": "划船。"
            },
            {
                "ja": "公園[こうえん]でボートに乗[の]ります。",
                "zh": "在公园坐小船。"
            },
            {
                "ja": "ボートレースを見[み]ます。",
                "zh": "看赛艇。"
            }
        ]
    },
    {
        "id": "N5_0773",
        "level": "N5",
        "expression": "ball pen",
        "kana": "ボールペン",
        "tone": "[0]",
        "pos": "名",
        "meaning": "圆珠笔",
        "examples": [
            {
                "ja": "ボールペンで書[か]きます。",
                "zh": "用圆珠笔写。"
            },
            {
                "ja": "黒[くろ]のボールペンがあります。",
                "zh": "有黑色的圆珠笔。"
            },
            {
                "ja": "ボールペンのインクが切[き]れました。",
                "zh": "圆珠笔没油了。"
            }
        ]
    },
    {
        "id": "N5_0774",
        "level": "N5",
        "expression": "他/外",
        "kana": "ほか",
        "tone": "[0]",
        "pos": "名",
        "meaning": "其他;超出",
        "examples": [
            {
                "ja": "他[ほか]の人[ひと]に聞[き]きます。",
                "zh": "问别人。"
            },
            {
                "ja": "思[おも]いの外[ほか]高[たか]かったです。",
                "zh": "出乎意料地贵。"
            },
            {
                "ja": "他[ほか]に何[なに]かありますか。",
                "zh": "还有其他的吗？"
            }
        ]
    },
    {
        "id": "N5_0775",
        "level": "N5",
        "expression": "僕",
        "kana": "ぼく",
        "tone": "①",
        "pos": "代",
        "meaning": "(男子自称）我",
        "examples": [
            {
                "ja": "僕[ぼく]は学生[がくせい]です。",
                "zh": "我是学生。"
            },
            {
                "ja": "僕[ぼく]の番[ばん]です。",
                "zh": "轮到我了。"
            },
            {
                "ja": "君[きみ]と僕[ぼく]。",
                "zh": "你和我。"
            }
        ]
    },
    {
        "id": "N5_0776",
        "level": "N5",
        "expression": "pocket",
        "kana": "ポケット",
        "tone": "②①",
        "pos": "名",
        "meaning": "口袋",
        "examples": [
            {
                "ja": "お金[かね]をポケットに入[い]れます。",
                "zh": "把钱放入口袋。"
            },
            {
                "ja": "ポケットサイズ。",
                "zh": "可放入口袋的大小。"
            },
            {
                "ja": "ポケットに手[て]を入[い]れます。",
                "zh": "把手插进布袋。"
            }
        ]
    },
    {
        "id": "N5_0777",
        "level": "N5",
        "expression": "欲しい",
        "kana": "ほしい",
        "tone": "②",
        "pos": "イ形",
        "meaning": "想要",
        "examples": [
            {
                "ja": "新[あたら]しい服[ふく]が欲[ほ]しいです。",
                "zh": "想要新衣服。"
            },
            {
                "ja": "時間[じかん]が欲[ほ]しいです。",
                "zh": "想要时间。"
            },
            {
                "ja": "何[なに]が欲[ほ]しいですか。",
                "zh": "想要什么？"
            }
        ]
    },
    {
        "id": "N5_0778",
        "level": "N5",
        "expression": "post",
        "kana": "ポスト",
        "tone": "①",
        "pos": "名",
        "meaning": "信箱，邮筒",
        "examples": [
            {
                "ja": "手紙[てがみ]をポストに入[い]れます。",
                "zh": "把信放入邮筒。"
            },
            {
                "ja": "赤[あか]いポストがあります。",
                "zh": "有红色的邮筒。"
            },
            {
                "ja": "ポストの前[まえ]で待[ま]ちます。",
                "zh": "在邮筒前等。"
            }
        ]
    },
    {
        "id": "N5_0779",
        "level": "N5",
        "expression": "細い",
        "kana": "ほそい",
        "tone": "②",
        "pos": "イ形",
        "meaning": "细的，窄的;瘦的",
        "examples": [
            {
                "ja": "細[ほそ]い道[みち]を行[い]きます。",
                "zh": "走小路。"
            },
            {
                "ja": "細[ほそ]い体[からだ]をしています。",
                "zh": "身材纤细。"
            },
            {
                "ja": "糸[いと]のように細[ほそ]いです。",
                "zh": "像线一样细。"
            }
        ]
    },
    {
        "id": "N5_0780",
        "level": "N5",
        "expression": "button",
        "kana": "ボタン",
        "tone": "[0]",
        "pos": "名",
        "meaning": "纽扣;按钮",
        "examples": [
            {
                "ja": "ボタンが取[と]れました。",
                "zh": "纽扣掉了。"
            },
            {
                "ja": "ボタンを押[お]します。",
                "zh": "按按钮。"
            },
            {
                "ja": "シャツのボタンを留[と]めます。",
                "zh": "扣上衬衫的扣子。"
            }
        ]
    },
    {
        "id": "N5_0781",
        "level": "N5",
        "expression": "potato",
        "kana": "ポテト",
        "tone": "①",
        "pos": "名",
        "meaning": "土豆，马铃薯",
        "examples": [
            {
                "ja": "ポテトチップスを食[た]べます。",
                "zh": "吃薯片。"
            },
            {
                "ja": "フライドポテト。",
                "zh": "炸薯条。"
            },
            {
                "ja": "ポテトサラダを作[つく]ります。",
                "zh": "做土豆沙拉。"
            }
        ]
    },
    {
        "id": "N5_0782",
        "level": "N5",
        "expression": "hotel",
        "kana": "ホテル",
        "tone": "①",
        "pos": "名",
        "meaning": "(西式）宾馆",
        "examples": [
            {
                "ja": "ホテルに泊[と]まります。",
                "zh": "住在宾馆里。"
            },
            {
                "ja": "ホテルを予約[よやく]します。",
                "zh": "预订宾馆。"
            },
            {
                "ja": "高級[こうきゅう]なホテルです。",
                "zh": "高级宾馆。"
            }
        ]
    },
    {
        "id": "N5_0783",
        "level": "N5",
        "expression": "本",
        "kana": "ほん",
        "tone": "①",
        "pos": "名",
        "meaning": "书本，书籍",
        "examples": [
            {
                "ja": "本[ほん]を読[よ]みます。",
                "zh": "读书。"
            },
            {
                "ja": "本[ほん]を買[か]います。",
                "zh": "买书。"
            },
            {
                "ja": "本[ほん]を借[か]ります。",
                "zh": "借书。"
            }
        ]
    },
    {
        "id": "N5_0784",
        "level": "N5",
        "expression": "～本",
        "kana": "～ほん",
        "tone": "",
        "pos": "接尾",
        "meaning": "(笔等细长的东西）支，把，瓶",
        "examples": [
            {
                "ja": "鉛筆[えんぴつ]を1本[いっぽん]買[か]います。",
                "zh": "买一支铅笔。"
            },
            {
                "ja": "ビールを6本[ろっぽん]飲[の]みます。",
                "zh": "喝六瓶啤酒。"
            },
            {
                "ja": "花[はな]が8本[はっぽん]あります。",
                "zh": "有八支花。"
            }
        ]
    },
    {
        "id": "N5_0785",
        "level": "N5",
        "expression": "本棚",
        "kana": "ほんだな",
        "tone": "①",
        "pos": "名",
        "meaning": "书柜，书架",
        "examples": [
            {
                "ja": "本棚[ほんだな]に本[ほん]を並[なら]べます。",
                "zh": "把书摆在书架上。"
            },
            {
                "ja": "本棚[ほんだな]を整理[せいり]します。",
                "zh": "整理书架。"
            },
            {
                "ja": "新[あたら]しい本棚[ほんだな]を買[か]いました。",
                "zh": "买了新书架。"
            }
        ]
    },
    {
        "id": "N5_0786",
        "level": "N5",
        "expression": "本当",
        "kana": "ほんとう",
        "tone": "[0]",
        "pos": "名*ナ形",
        "meaning": "真实，事实;真的",
        "examples": [
            {
                "ja": "本当[ほんとう]のことを言[い]います。",
                "zh": "说实话。"
            },
            {
                "ja": "それは本当[ほんとう]ですか。",
                "zh": "那是真的吗？"
            },
            {
                "ja": "本当[ほんとう]の気持[きも]ち。",
                "zh": "真实的心情。"
            }
        ]
    },
    {
        "id": "N5_0787",
        "level": "N5",
        "expression": "本当に",
        "kana": "ほんとうに",
        "tone": "[0]",
        "pos": "副",
        "meaning": "真的，非常",
        "examples": [
            {
                "ja": "本当[ほんとう]にありがとうございました。",
                "zh": "真心感谢。"
            },
            {
                "ja": "本当[ほんとう]に難[むずか]しいです。",
                "zh": "非常难。"
            },
            {
                "ja": "本当[ほんとう]においしいです。",
                "zh": "真的很好吃。"
            }
        ]
    },
    {
        "id": "N5_0788",
        "level": "N5",
        "expression": "マージャン",
        "kana": "マージャン",
        "tone": "[0]①",
        "pos": "名",
        "meaning": "麻将",
        "examples": [
            {
                "ja": "マージャンをします。",
                "zh": "打麻将。"
            },
            {
                "ja": "友達[ともだち]とマージャンを楽[たの]しみます。",
                "zh": "和朋友开心打麻将。"
            },
            {
                "ja": "マージャンのルールを覚[おぼ]えます。",
                "zh": "记麻将规则。"
            }
        ]
    },
    {
        "id": "N5_0789",
        "level": "N5",
        "expression": "毎～",
        "kana": "まい～",
        "tone": "",
        "pos": "接頭",
        "meaning": "每个······",
        "examples": [
            {
                "ja": "毎回[まいかい]参加[さんか]します。",
                "zh": "每次都参加。"
            },
            {
                "ja": "毎度[まいど]ありがとうございます。",
                "zh": "每次都谢谢惠顾。"
            },
            {
                "ja": "毎日[まいにち]勉強[べんきょう]します。",
                "zh": "每天学习。"
            }
        ]
    },
    {
        "id": "N5_0790",
        "level": "N5",
        "expression": "～枚",
        "kana": "～まい",
        "tone": "",
        "pos": "接尾",
        "meaning": "(盘碟等薄片类的物体）……张，……枚",
        "examples": [
            {
                "ja": "紙[かみ]を1枚[いちまい]ください。",
                "zh": "请给我一张纸。"
            },
            {
                "ja": "お皿[さら]を2枚[にまい]洗[あら]います。",
                "zh": "洗两只盘子。"
            },
            {
                "ja": "写真[しゃしん]を何枚[なんまい]撮[と]りましたか。",
                "zh": "拍了几张照片？"
            }
        ]
    },
    {
        "id": "N5_0791",
        "level": "N5",
        "expression": "毎朝",
        "kana": "まいあさ",
        "tone": "①[0]",
        "pos": "名",
        "meaning": "每天早上",
        "examples": [
            {
                "ja": "毎朝[まいあさ]7時[しちじ]に起[お]きます。",
                "zh": "每天早上七点钟起床。"
            },
            {
                "ja": "毎朝[まいあさ]コーヒーを飲[の]みます。",
                "zh": "每天早上喝咖啡。"
            },
            {
                "ja": "毎朝[まいあさ]ジョギングをします。",
                "zh": "每天早上慢跑。"
            }
        ]
    },
    {
        "id": "N5_0792",
        "level": "N5",
        "expression": "毎回",
        "kana": "まいかい",
        "tone": "[0]",
        "pos": "副",
        "meaning": "每次，每回",
        "examples": [
            {
                "ja": "毎回[まいかい]出席[しゅっせき]します。",
                "zh": "每回都出席。"
            },
            {
                "ja": "毎回[まいかい]同[おな]じことを言[い]います。",
                "zh": "每次都说同样的话。"
            },
            {
                "ja": "毎回[まいかい]楽[たの]しみにしています。",
                "zh": "每次都很期待。"
            }
        ]
    },
    {
        "id": "N5_0793",
        "level": "N5",
        "expression": "毎月",
        "kana": "まいげつ/まいつき",
        "tone": "[0]",
        "pos": "名",
        "meaning": "每个月",
        "examples": [
            {
                "ja": "メニューは毎月[まいげつ]変[か]わります。",
                "zh": "每个月更换菜单。"
            },
            {
                "ja": "毎月[まいげつ]貯金[ちょきん]します。",
                "zh": "每个月存钱。"
            },
            {
                "ja": "毎月[まいげつ]の手紙[てがみ]。",
                "zh": "每月的信。"
            }
        ]
    },
    {
        "id": "N5_0794",
        "level": "N5",
        "expression": "迷子",
        "kana": "まいご",
        "tone": "①",
        "pos": "名",
        "meaning": "迷路的孩子",
        "examples": [
            {
                "ja": "迷子[まいご]になりました。",
                "zh": "迷路了。"
            },
            {
                "ja": "デパートで迷子[まいご]の放送[ほうそう]があります。",
                "zh": "百货公司有寻找迷路儿童的广播。"
            },
            {
                "ja": "迷子[まいご]センター。",
                "zh": "走失儿童中心。"
            }
        ]
    },
    {
        "id": "N5_0795",
        "level": "N5",
        "expression": "毎週",
        "kana": "まいしゅう",
        "tone": "[0]",
        "pos": "名",
        "meaning": "每周",
        "examples": [
            {
                "ja": "毎週[まいしゅう]の日曜日[にちようび]。",
                "zh": "每个周曰。"
            },
            {
                "ja": "毎週[まいしゅう]テニスをします。",
                "zh": "每周打网球。"
            },
            {
                "ja": "毎週[まいしゅう]テストがあります。",
                "zh": "每周有考试。"
            }
        ]
    },
    {
        "id": "N5_0796",
        "level": "N5",
        "expression": "毎年",
        "kana": "まいとし/まいねん",
        "tone": "[0]",
        "pos": "名",
        "meaning": "每年",
        "examples": [
            {
                "ja": "毎年[まいとし]一回[いっかい]海外[かいがい]へ旅行[りょこう]します。",
                "zh": "毎年去国外旅游一次。"
            },
            {
                "ja": "毎年[まいとし]帰省[きせい]します。",
                "zh": "每年回老家。"
            },
            {
                "ja": "毎年[まいとし]の行事[ぎょうじ]。",
                "zh": "每年的活动。"
            }
        ]
    },
    {
        "id": "N5_0797",
        "level": "N5",
        "expression": "毎日",
        "kana": "まいにち",
        "tone": "①",
        "pos": "名",
        "meaning": "每天",
        "examples": [
            {
                "ja": "毎日[まいにち]散歩[さんぽ]します。",
                "zh": "每天都要散歩。"
            },
            {
                "ja": "毎日[まいにち]日本語[にほんご]を勉強[べんきょう]します。",
                "zh": "每天学习日语。"
            },
            {
                "ja": "毎日[まいにち]楽[たの]しいです。",
                "zh": "每天都很开心。"
            }
        ]
    },
    {
        "id": "N5_0798",
        "level": "N5",
        "expression": "毎晚",
        "kana": "まいばん",
        "tone": "①[0]",
        "pos": "名",
        "meaning": "每晚",
        "examples": [
            {
                "ja": "毎晚[まいばん]ミルクを飲[の]みます。",
                "zh": "每天晚上都要喝牛奶。"
            },
            {
                "ja": "毎晚[まいばん]テレビを見[み]ます。",
                "zh": "每天晚上看电视。"
            },
            {
                "ja": "毎晚[まいばん]遅[おそ]くまで起[お]きています。",
                "zh": "每晚都熬夜。"
            }
        ]
    },
    {
        "id": "N5_0799",
        "level": "N5",
        "expression": "前",
        "kana": "まえ",
        "tone": "①",
        "pos": "名",
        "meaning": "(空间上的）前面；（时间上的）以前",
        "examples": [
            {
                "ja": "駅[えき]の前[まえ]に本屋[ほんや]があります。",
                "zh": "车站前有一家书店。"
            },
            {
                "ja": "寝[ね]る前[まえ]にシャワーを浴[あ]びます。",
                "zh": "睡前洗澡。"
            },
            {
                "ja": "3年[ねん]前[まえ]に来[き]ました。",
                "zh": "三年前来的。"
            }
        ]
    },
    {
        "id": "N5_0800",
        "level": "N5",
        "expression": "～前",
        "kana": "～まえ",
        "tone": "",
        "pos": "接尾",
        "meaning": "……份;气度",
        "examples": [
            {
                "ja": "5人前[ごにんまえ]ください。",
                "zh": "请给我五人份。"
            },
            {
                "ja": "彼[かれ]は男前[おとこまえ]です。",
                "zh": "他很有男子气概。"
            },
            {
                "ja": "一人前[いちにんまえ]になります。",
                "zh": "能够独当一面。"
            }
        ]
    }
]